{
    "summon": "--",
    "templateType": "Creature",
    "plural": "pillars",
    "hpDrainDmgMod": "0%",
    "notes": "They don't harm your [[Hitpoints]] like similar traps.",
    "walksthrough": "None",
    "hp": "120",
    "speed": "0",
    "abilities": "{{Ability List\n |{{Debuff2|shielding=yes|value=90-95%|scene={{Scene|spell=7sqmstrike|caster=Pillar (Zugurosh)|caster_name=|look_direction=south|effect=Cloud Effect|missile=Death Missile (Large)|missile_direction=south-east|missile_distance=7/7}}}}\n}}",
    "pushobjects": "?",
    "healMod": "100%?",
    "paraimmune": "yes",
    "fireDmgMod": "0%",
    "holyDmgMod": "0%",
    "sounds": [],
    "maxdmg": "0",
    "pushable": "?",
    "implemented": "8.20",
    "loot": [],
    "walksaround": "None",
    "exp": "0",
    "creatureclass": "Special",
    "earthDmgMod": "0%",
    "physicalDmgMod": "0%",
    "primarytype": "Traps",
    "senseinvis": "yes",
    "article": "a",
    "actualname": "pillar",
    "illusionable": "no",
    "armor": "?",
    "drownDmgMod": "0%",
    "convince": "--",
    "name": "Pillar (Zugurosh)",
    "isboss": "no",
    "behaviour": "'''Pillars''' are unable to move.",
    "location": "[[The Inquisition Quest|Zugurosh's Room]].",
    "iceDmgMod": "0%",
    "strategy": "Ignore them.",
    "energyDmgMod": "0%",
    "deathDmgMod": "0%"
}