{
    "summon": "--",
    "templateType": "Creature",
    "plural": "symbols of hatred",
    "hpDrainDmgMod": "100%?",
    "notes": "None.",
    "walksthrough": "Fire, Energy, Poison",
    "hp": "?",
    "abilities": "{{Ability List| {{Melee|?}} }}",
    "pushobjects": "yes",
    "healMod": "100%",
    "paraimmune": "yes",
    "fireDmgMod": "100%?",
    "holyDmgMod": "100%?",
    "sounds": [
        ""
    ],
    "pushable": "no",
    "implemented": "12.40.9997",
    "loot": [],
    "walksaround": "None",
    "exp": "?",
    "creatureclass": "Special Creatures",
    "earthDmgMod": "100%?",
    "physicalDmgMod": "100%?",
    "primarytype": "Traps",
    "spawntype": [
        "Unblockable"
    ],
    "senseinvis": "yes",
    "article": "a",
    "actualname": "symbol of hatred",
    "illusionable": "no",
    "armor": "?",
    "drownDmgMod": "100%?",
    "convince": "--",
    "name": "Symbol of Hatred",
    "isboss": "no",
    "behaviour": "Unknown.",
    "location": "The room of [[Goshnar's Hatred]].",
    "iceDmgMod": "100%?",
    "strategy": "None.",
    "energyDmgMod": "100%?",
    "deathDmgMod": "100%?"
}