{
    "summon": "--",
    "templateType": "Creature",
    "plural": "The Remorseless Corruptor",
    "hpDrainDmgMod": "100%?",
    "notes": "{{JSpoiler|Part of the [[Cults of Tibia Quest]].}}",
    "walksthrough": "?",
    "hp": "?",
    "speed": "?",
    "abilities": "{{Ability List|}}",
    "pushobjects": "?",
    "healMod": "100%?",
    "paraimmune": "?",
    "secondarytype": "Electro-Elementals",
    "fireDmgMod": "0%",
    "holyDmgMod": "0%",
    "sounds": [
        ""
    ],
    "maxdmg": "?",
    "pushable": "?",
    "implemented": "11.40.5409",
    "loot": [],
    "walksaround": "?",
    "exp": "?",
    "creatureclass": "Invertebrates",
    "earthDmgMod": "0%",
    "physicalDmgMod": "0%",
    "primarytype": "Cnidarians",
    "race_id": "1497",
    "senseinvis": "?",
    "actualname": "The Remorseless Corruptor",
    "illusionable": "no",
    "armor": "?",
    "drownDmgMod": "100%?",
    "convince": "--",
    "name": "The Remorseless Corruptor",
    "isboss": "yes",
    "behaviour": "Unknown",
    "location": "Unknown",
    "iceDmgMod": "0%",
    "strategy": "It's invulnerable, but it will become [[The Corruptor Of Souls|weaker]] if you apply some [[Guilt (Item)|Guilt]] on it.",
    "energyDmgMod": "0%",
    "deathDmgMod": "0%"
}