{
    "summon": "--",
    "templateType": "Creature",
    "hpDrainDmgMod": "0%",
    "notes": "None.",
    "walksthrough": "?",
    "hp": "--",
    "usespells": "yes",
    "speed": "?",
    "abilities": "{{Ability List\n |{{Ability|Polymorph|Can change any player or creature's appearance into either a [[Green Frog]], a [[Pig]], a [[Skunk]] or a [[Football]]|element=shapeshifting}}\n}}",
    "pushobjects": "?",
    "healMod": "100%?",
    "paraimmune": "yes",
    "secondarytype": "Imps",
    "fireDmgMod": "0%",
    "holyDmgMod": "0%",
    "sounds": [
        "I am so proud of my son Orshabaal.",
        "Have you heard, the imperor is marrying an imp named April? What a fool.",
        "The Ruthless Seven are going to make the easter bunny an honorary member!",
        "They are coming ... perhaps for YOU!",
        "Beware! The Ruthless Seven are coming!",
        "Killing me is imp-ossible, because I am imp-roved! I am immune to any imp-act!",
        "The one who kills me gets an imp-outfit.",
        "Hey you! I've heard that! You're first to die when the masters come.",
        "Nice to meet you. I am Harold, the ruthless herald.",
        "Have you seen my friend Harvey? I could swear he's somewhere around.",
        "My masters are on their way!"
    ],
    "maxdmg": "0",
    "pushable": "?",
    "implemented": "7.92",
    "loot": [],
    "walksaround": "?",
    "exp": "--",
    "creatureclass": "Special",
    "earthDmgMod": "0%",
    "physicalDmgMod": "0%",
    "primarytype": "Event Creatures",
    "attacktype": "Distance",
    "senseinvis": "yes",
    "illusionable": "no",
    "armor": "?",
    "drownDmgMod": "0%",
    "convince": "--",
    "name": "The Ruthless Herald",
    "isboss": "no",
    "location": "Roams around [[Mainland]].",
    "iceDmgMod": "0%",
    "strategy": "No strategy needed, as it doesn't do any damage nor can it be killed. Some players enjoy trapping it.",
    "energyDmgMod": "0%",
    "deathDmgMod": "0%",
    "status": "deprecated"
}