{
    "summon": "--",
    "templateType": "Creature",
    "hpDrainDmgMod": "100%?",
    "notes": "Do not walk near this creature as it will teleport you to the entrance of the dungeon and make you lose all your [[Luminescent Crystal]]s.",
    "walksthrough": "?",
    "hp": "?",
    "speed": "?",
    "abilities": "{{Ability List|}}",
    "pushobjects": "yes",
    "healMod": "100%",
    "paraimmune": "yes",
    "fireDmgMod": "0%",
    "holyDmgMod": "0%",
    "sounds": [
        ""
    ],
    "maxdmg": "?",
    "pushable": "no",
    "implemented": "12.30.9287",
    "loot": [],
    "walksaround": "?",
    "exp": "?",
    "creatureclass": "The Undead",
    "earthDmgMod": "0%",
    "physicalDmgMod": "0%",
    "primarytype": "Ghosts",
    "spawntype": [
        "Regular"
    ],
    "senseinvis": "yes",
    "article": "a",
    "actualname": "wandering prospector",
    "illusionable": "no",
    "armor": "?",
    "drownDmgMod": "100%?",
    "convince": "--",
    "name": "Wandering Prospector",
    "isboss": "no",
    "behaviour": "Unknown.",
    "location": "[[Barren Drift]]",
    "iceDmgMod": "0%",
    "energyDmgMod": "0%",
    "deathDmgMod": "0%"
}